mpstool/__init__.py
mpstool/connectivity.py
mpstool/cv_metrics.py
mpstool/img.py
mpstool/stats.py
mpstool/variogram.py
mpstool-1.2.0.dist-info/LICENSE
mpstool-1.2.0.dist-info/METADATA
mpstool-1.2.0.dist-info/WHEEL
mpstool-1.2.0.dist-info/top_level.txt
mpstool-1.2.0.dist-info/RECORD
