Metadata-Version: 2.1
Name: mpstool
Version: 1.2.0
Summary: Multiple-point statistics toolbox
Home-page: https://github.com/UniNE-CHYN/mps_toolbox
Author: randlab
License: MIT
Platform: UNKNOWN
Classifier: License :: OSI Approved :: MIT License
Classifier: Programming Language :: Python
Classifier: Programming Language :: Python :: 3
Requires-Dist: numpy
Requires-Dist: scikit-image
Requires-Dist: py-vox-io
Requires-Dist: properscoring
Requires-Dist: Pillow
